[
  {
    "brand": "EXOFLEX",
    "weight_raw": 1000,
    "website": "https://exoflex.ru/",
    "weight_g": 155,
    "diameter_mm": 196,
    "width_mm": 74,
    "inner_diameter_mm": 52,
    "filament_hole_mm": 84,
    "id": "exoflex_155",
    "type": null,
    "author_rating": null,
    "author_review": null,
    "filament_profiles": [],
    "reviews_discussion_url": null,
    "notes": null,
    "poop_rating": false
  },
  {
    "brand": "MAKO",
    "weight_raw": "1000г",
    "website": "https://3dmako.ru/",
    "weight_g": 182,
    "diameter_mm": 200,
    "width_mm": 70,
    "inner_diameter_mm": 52,
    "filament_hole_mm": 110,
    "id": "mako_182",
    "type": null,
    "author_rating": null,
    "author_review": null,
    "filament_profiles": [],
    "reviews_discussion_url": null,
    "notes": null,
    "poop_rating": false
  },
  {
    "brand": "СТРИМПЛАСТ",
    "weight_raw": "500г / 750г   800г / 1000г",
    "website": "Расходные FDM (FFF) материалы ECOFIL",
    "weight_g": 174,
    "diameter_mm": 202,
    "width_mm": 56,
    "inner_diameter_mm": 52,
    "filament_hole_mm": 110,
    "id": "стримпласт_174",
    "type": null,
    "author_rating": null,
    "author_review": null,
    "filament_profiles": [],
    "reviews_discussion_url": null,
    "notes": null,
    "poop_rating": false
  },
  {
    "brand": "CYBERFIBER",
    "weight_raw": "750г",
    "website": "CYBERFIBER",
    "weight_g": null,
    "diameter_mm": null,
    "width_mm": null,
    "inner_diameter_mm": null,
    "filament_hole_mm": null,
    "id": "cyberfiber_null",
    "type": null,
    "author_rating": null,
    "author_review": null,
    "filament_profiles": [],
    "reviews_discussion_url": null,
    "notes": null,
    "poop_rating": false
  },
  {
    "brand": "FDplast",
    "weight_raw": "750 г",
    "website": "Пластик для 3D принтера",
    "weight_g": null,
    "diameter_mm": null,
    "width_mm": null,
    "inner_diameter_mm": null,
    "filament_hole_mm": null,
    "id": "fdplast_null",
    "type": null,
    "author_rating": null,
    "author_review": null,
    "filament_profiles": [],
    "reviews_discussion_url": null,
    "notes": null,
    "poop_rating": false
  },
  {
    "brand": "FILAMENTARNO",
    "weight_raw": "750 г",
    "website": "http://filamentarno.ru/catalog.html",
    "weight_g": null,
    "diameter_mm": null,
    "width_mm": null,
    "inner_diameter_mm": null,
    "filament_hole_mm": null,
    "id": "filamentarno_null",
    "type": null,
    "author_rating": null,
    "author_review": null,
    "filament_profiles": [],
    "reviews_discussion_url": null,
    "notes": null,
    "poop_rating": false
  },
  {
    "brand": "gReg",
    "weight_raw": "300 м",
    "website": "https://greg-3d.ru/Expendables.Filament.php",
    "weight_g": null,
    "diameter_mm": null,
    "width_mm": null,
    "inner_diameter_mm": null,
    "filament_hole_mm": null,
    "id": "greg_null",
    "type": null,
    "author_rating": null,
    "author_review": null,
    "filament_profiles": [],
    "reviews_discussion_url": null,
    "notes": null,
    "poop_rating": false
  },
  {
    "brand": "MY3D",
    "weight_raw": "750г / 1000г",
    "website": "PETG - филаменты для 3d печати",
    "weight_g": null,
    "diameter_mm": null,
    "width_mm": null,
    "inner_diameter_mm": null,
    "filament_hole_mm": null,
    "id": "my3d_null",
    "type": null,
    "author_rating": null,
    "author_review": null,
    "filament_profiles": [],
    "reviews_discussion_url": null,
    "notes": null,
    "poop_rating": false
  },
  {
    "brand": "REC",
    "weight_raw": "2000 гр",
    "website": "RELAX пластик REC 1.75мм чёрный 2кг",
    "weight_g": 601,
    "diameter_mm": 300,
    "width_mm": 100,
    "inner_diameter_mm": 200,
    "filament_hole_mm": 100,
    "id": "rec_601",
    "type": null,
    "author_rating": null,
    "author_review": null,
    "filament_profiles": [],
    "reviews_discussion_url": null,
    "notes": null,
    "poop_rating": false
  },
  {
    "brand": "SEM",
    "weight_raw": "500г / 800г  950г",
    "website": "https://sem3d.ru/",
    "weight_g": null,
    "diameter_mm": null,
    "width_mm": null,
    "inner_diameter_mm": null,
    "filament_hole_mm": null,
    "id": "sem_null",
    "type": null,
    "author_rating": null,
    "author_review": null,
    "filament_profiles": [],
    "reviews_discussion_url": null,
    "notes": null,
    "poop_rating": false
  },
  {
    "brand": "СТРИМПЛАСТ",
    "weight_raw": "1000 г",
    "website": "https://www.sp3d.ru/collection/rashodnye-materialy-fdm",
    "weight_g": 224,
    "diameter_mm": 197,
    "width_mm": 56,
    "inner_diameter_mm": 52,
    "filament_hole_mm": 89,
    "id": "стримпласт_224",
    "type": null,
    "author_rating": null,
    "author_review": null,
    "filament_profiles": [],
    "reviews_discussion_url": null,
    "notes": null,
    "poop_rating": false
  },
  {
    "brand": "CYBERFIBER",
    "weight_raw": "450г / 750г",
    "website": "http://www.cyberfiber.ru/",
    "weight_g": null,
    "diameter_mm": null,
    "width_mm": null,
    "inner_diameter_mm": null,
    "filament_hole_mm": null,
    "id": "cyberfiber_null",
    "type": null,
    "author_rating": null,
    "author_review": null,
    "filament_profiles": [],
    "reviews_discussion_url": null,
    "notes": null,
    "poop_rating": false
  },
  {
    "brand": "PRINT PRODUCT",
    "weight_raw": "300г / 500г / 1000г",
    "website": "Товары для 3D–печати от производителя",
    "weight_g": null,
    "diameter_mm": null,
    "width_mm": null,
    "inner_diameter_mm": null,
    "filament_hole_mm": null,
    "id": "print_product_null",
    "type": null,
    "author_rating": null,
    "author_review": null,
    "filament_profiles": [],
    "reviews_discussion_url": null,
    "notes": null,
    "poop_rating": false
  },
  {
    "brand": "BestFilament",
    "weight_raw": "1000 г ",
    "website": "Bestfilament пластик для 3д-принтеров",
    "weight_g": 177,
    "diameter_mm": 200,
    "width_mm": "65 или 57",
    "inner_diameter_mm": 52,
    "filament_hole_mm": 73,
    "id": "bestfilament_177",
    "type": null,
    "author_rating": null,
    "author_review": null,
    "filament_profiles": [],
    "reviews_discussion_url": null,
    "notes": null,
    "poop_rating": false
  },
  {
    "brand": "FDplast",
    "weight_raw": "1000 г",
    "website": "Пластик для 3D принтера",
    "weight_g": "195-        215",
    "diameter_mm": 188,
    "width_mm": "4кка443",
    "inner_diameter_mm": 52,
    "filament_hole_mm": 99,
    "id": "fdplast_195-215",
    "type": null,
    "author_rating": null,
    "author_review": null,
    "filament_profiles": [],
    "reviews_discussion_url": null,
    "notes": null,
    "poop_rating": false
  },
  {
    "brand": "U3 Print /                               Geek Fil/lament",
    "weight_raw": "450 г / 1000 г",
    "website": "Пластик для 3D принтера - купить в Москве",
    "weight_g": 256,
    "diameter_mm": 200,
    "width_mm": 69,
    "inner_diameter_mm": 83,
    "filament_hole_mm": 90,
    "id": "u3_print_/_______________________________geek_fil/lament_256",
    "type": null,
    "author_rating": null,
    "author_review": null,
    "filament_profiles": [],
    "reviews_discussion_url": null,
    "notes": null,
    "poop_rating": false
  },
  {
    "brand": "PRINT PRODUCT",
    "weight_raw": "1000 г",
    "website": "Товары для 3D–печати от производителя",
    "weight_g": 261,
    "diameter_mm": 190,
    "width_mm": 84,
    "inner_diameter_mm": 39,
    "filament_hole_mm": 100,
    "id": "print_product_261",
    "type": null,
    "author_rating": null,
    "author_review": null,
    "filament_profiles": [],
    "reviews_discussion_url": null,
    "notes": null,
    "poop_rating": false
  },
  {
    "brand": "ABS Maker",
    "weight_raw": "1000 г",
    "website": "ABSMaker",
    "weight_g": 178,
    "diameter_mm": 198,
    "width_mm": 75,
    "inner_diameter_mm": 52,
    "filament_hole_mm": 110,
    "id": "abs_maker_178",
    "type": null,
    "author_rating": null,
    "author_review": null,
    "filament_profiles": [],
    "reviews_discussion_url": null,
    "notes": null,
    "poop_rating": false
  },
  {
    "brand": "Solidfilament",
    "weight_raw": "300г / 500г / 1000г",
    "website": "https://top3dshop.ru/materiali/",
    "weight_g": 195,
    "diameter_mm": "?",
    "width_mm": "?",
    "inner_diameter_mm": "?",
    "filament_hole_mm": "?",
    "id": "solidfilament_195",
    "type": null,
    "author_rating": null,
    "author_review": null,
    "filament_profiles": [],
    "reviews_discussion_url": null,
    "notes": null,
    "poop_rating": false
  },
  {
    "brand": "eSUN",
    "weight_raw": "1000 г",
    "website": "Каталог",
    "weight_g": 215,
    "diameter_mm": 200,
    "width_mm": 61,
    "inner_diameter_mm": 52,
    "filament_hole_mm": 90,
    "id": "esun_215",
    "type": null,
    "author_rating": null,
    "author_review": null,
    "filament_profiles": [],
    "reviews_discussion_url": null,
    "notes": null,
    "poop_rating": false
  },
  {
    "brand": "SynTech",
    "weight_raw": "1000 г",
    "website": "https://www.syntechlab.ru/",
    "weight_g": 42,
    "diameter_mm": 195,
    "width_mm": 65,
    "inner_diameter_mm": 54,
    "filament_hole_mm": 60,
    "id": "syntech_42",
    "type": null,
    "author_rating": null,
    "author_review": null,
    "filament_profiles": [],
    "reviews_discussion_url": null,
    "notes": null,
    "poop_rating": false
  },
  {
    "brand": "Hi-Tech Plast",
    "weight_raw": "850 г / 1000 г",
    "website": "http://h-t-p.ru/",
    "weight_g": 44,
    "diameter_mm": 185,
    "width_mm": 75,
    "inner_diameter_mm": 49,
    "filament_hole_mm": "?",
    "id": "hi-tech_plast_44",
    "type": null,
    "author_rating": null,
    "author_review": null,
    "filament_profiles": [],
    "reviews_discussion_url": null,
    "notes": null,
    "poop_rating": false
  },
  {
    "brand": "Некрасовский полимер",
    "weight_raw": "1000 г",
    "website": "https://www.p8kvt.ru/PETG-Пластик-для-3D-принтера-1-75-мм-1-кг-Некрасовский-полимер-Серия-Мастерская-p436608069",
    "weight_g": 171,
    "diameter_mm": 200,
    "width_mm": 73,
    "inner_diameter_mm": 52,
    "filament_hole_mm": 109.5,
    "id": "некрасовский_полимер_171",
    "type": null,
    "author_rating": null,
    "author_review": null,
    "filament_profiles": [],
    "reviews_discussion_url": null,
    "notes": null,
    "poop_rating": false
  },
  {
    "brand": "НИТ",
    "weight_raw": "1000 г",
    "website": "ПК НИТ",
    "weight_g": 183,
    "diameter_mm": 200,
    "width_mm": 75,
    "inner_diameter_mm": 53,
    "filament_hole_mm": 110,
    "id": "нит_183",
    "type": null,
    "author_rating": null,
    "author_review": null,
    "filament_profiles": [],
    "reviews_discussion_url": null,
    "notes": null,
    "poop_rating": true
  },
  {
    "brand": "Kingroon",
    "weight_raw": "1000 г",
    "website": null,
    "weight_g": 185,
    "diameter_mm": null,
    "width_mm": null,
    "inner_diameter_mm": null,
    "filament_hole_mm": null,
    "id": "kingroon_185",
    "type": null,
    "author_rating": null,
    "author_review": null,
    "filament_profiles": [],
    "reviews_discussion_url": null,
    "notes": null,
    "poop_rating": false
  },
  {
    "brand": "ERYONE",
    "weight_raw": "1000 г",
    "website": "https://eryone.com/products/filament/",
    "weight_g": 192,
    "diameter_mm": 200,
    "width_mm": 62,
    "inner_diameter_mm": 54,
    "filament_hole_mm": 90,
    "id": "eryone_192",
    "type": null,
    "author_rating": null,
    "author_review": null,
    "filament_profiles": [],
    "reviews_discussion_url": null,
    "notes": null,
    "poop_rating": false
  },
  {
    "brand": "Creality hyper series",
    "weight_raw": "1000 г. ",
    "website": null,
    "weight_g": "164.9",
    "diameter_mm": 197,
    "width_mm": 64.5,
    "inner_diameter_mm": 55.5,
    "filament_hole_mm": 86.8,
    "id": "creality_hyper_series_164.9",
    "type": null,
    "author_rating": null,
    "author_review": null,
    "filament_profiles": [],
    "reviews_discussion_url": null,
    "notes": null,
    "poop_rating": false
  },
  {
    "brand": "3D printer filament T-ABS, PopBit",
    "weight_raw": " 1000 г.",
    "website": null,
    "weight_g": 195,
    "diameter_mm": 198,
    "width_mm": 67,
    "inner_diameter_mm": 58,
    "filament_hole_mm": 79,
    "id": "3d_printer_filament_t-abs,_popbit_195",
    "type": null,
    "author_rating": null,
    "author_review": null,
    "filament_profiles": [],
    "reviews_discussion_url": null,
    "notes": null,
    "poop_rating": false
  },
  {
    "brand": "Eryone ",
    "weight_raw": "1000 г. ",
    "website": null,
    "weight_g": "187.4",
    "diameter_mm": 199,
    "width_mm": 63.9,
    "inner_diameter_mm": 53.9,
    "filament_hole_mm": 87,
    "id": "eryone_187.4",
    "type": null,
    "author_rating": null,
    "author_review": null,
    "filament_profiles": [],
    "reviews_discussion_url": null,
    "notes": null,
    "poop_rating": false
  },
  {
    "brand": "123D",
    "weight_raw": "1000 г.",
    "website": null,
    "weight_g": 221,
    "diameter_mm": 172,
    "width_mm": 64,
    "inner_diameter_mm": 25.5,
    "filament_hole_mm": 89,
    "id": "123d_221",
    "type": null,
    "author_rating": null,
    "author_review": null,
    "filament_profiles": [],
    "reviews_discussion_url": null,
    "notes": null,
    "poop_rating": false
  },
  {
    "brand": "FILAMENTARNO",
    "weight_raw": "750 г.",
    "website": null,
    "weight_g": "200 - 206",
    "diameter_mm": null,
    "width_mm": null,
    "inner_diameter_mm": null,
    "filament_hole_mm": null,
    "id": "filamentarno_200-206",
    "type": null,
    "author_rating": null,
    "author_review": null,
    "filament_profiles": [],
    "reviews_discussion_url": null,
    "notes": null,
    "poop_rating": false
  },
  {
    "brand": "FDplast",
    "weight_raw": "1000 г",
    "website": "Пластик для 3D принтера",
    "weight_g": 355,
    "diameter_mm": null,
    "width_mm": null,
    "inner_diameter_mm": null,
    "filament_hole_mm": null,
    "id": "fdplast_355",
    "type": null,
    "author_rating": null,
    "author_review": null,
    "filament_profiles": [],
    "reviews_discussion_url": null,
    "notes": null,
    "poop_rating": false
  },
  {
    "brand": "Geeetech ",
    "weight_raw": 1000,
    "website": "tpu a95",
    "weight_g": 187,
    "diameter_mm": 195,
    "width_mm": 65,
    "inner_diameter_mm": 75,
    "filament_hole_mm": 78,
    "id": "geeetech_187",
    "type": null,
    "author_rating": null,
    "author_review": null,
    "filament_profiles": [],
    "reviews_discussion_url": null,
    "notes": null,
    "poop_rating": false
  }
]
